R2SAScore/R2SAScore.py
R2SAScore/__init__.py
R2SAScore/pickle/BScores_emolecules.pkl.gz
R2SAScore/pickle/R2SAScores_uspto_emolecules.pkl.gz
R2SAScore/pickle/RScores_uspto.pkl.gz
R2SAScore-0.1.0.dist-info/LICENSE
R2SAScore-0.1.0.dist-info/METADATA
R2SAScore-0.1.0.dist-info/WHEEL
R2SAScore-0.1.0.dist-info/top_level.txt
R2SAScore-0.1.0.dist-info/RECORD
